charcounter/__init__.py
charcounter/__main__.py
charcounter/app/__init__.py
charcounter/app/app.py
charcounter/utils/__init__.py
charcounter/utils/exceptions.py
charcounter/utils/functions.py
charcounter-1.1.dist-info/LICENSE
charcounter-1.1.dist-info/METADATA
charcounter-1.1.dist-info/WHEEL
charcounter-1.1.dist-info/entry_points.txt
charcounter-1.1.dist-info/top_level.txt
charcounter-1.1.dist-info/RECORD
