Metadata-Version: 2.1
Name: charcounter
Version: 1.1
Summary: Calculate count of unique characters in a string or file
Home-page: UNKNOWN
Author: Dihtiar Vadym
License: UNKNOWN
Platform: UNKNOWN
Requires-Python: >=3.8
License-File: LICENSE
Requires-Dist: pytest (==7.2.0)
